chia_tools/__init__.py
chia_tools/convert_json_results_to_pandas.py
chia_tools/create_config_grid.py
chia_tools/json_result_viewer.py
chia_tools/validate_dataset.py
chia_tools/version.py
chia_tools/ui/json_result_viewer.ui
chia_tools-1.2.dist-info/METADATA
chia_tools-1.2.dist-info/WHEEL
chia_tools-1.2.dist-info/top_level.txt
chia_tools-1.2.dist-info/RECORD
