Metadata-Version: 2.1
Name: chia-tools
Version: 1.2
Summary: Extra tools for the CHIA framework
Home-page: https://github.com/cabrust/chia-tools
Author: Clemens-Alexander Brust
Author-email: clemens-alexander.brust@uni-jena.de
License: UNKNOWN
Platform: UNKNOWN
Classifier: Programming Language :: Python :: 3.7
Classifier: Programming Language :: Python :: 3.8
Classifier: Programming Language :: Python :: 3.9
Requires-Python: >=3.7
Requires-Dist: tqdm (~=4.51)
Requires-Dist: tables (~=3.6.1)
Requires-Dist: pandas (~=1.0.4)
Requires-Dist: pyqt5 (~=5.15.0)
Requires-Dist: matplotlib (~=3.2.1)
Requires-Dist: chia (~=2.4.0)
